{"id":"406B8218-A615-4F78-A74E-484E5B8246EE","name":"default_406B8218-A615-4F78-A74E-484E5B8246EE","drawings":[{"id":"09DB353C-D205-4538-92B3-3D9EB67390CD","strokes":[{"id":"3CD9F369-CBB4-4AA1-8036-F8AD7350CE98","time":"0.680457","segments":[{"point":{"x":353,"y":641.5},"time":0.00224799},{"point":{"x":350.5,"y":641.5},"time":0.003447},{"point":{"x":344,"y":644},"time":0.032925},{"point":{"x":344,"y":645.5},"time":0.050981},{"point":{"x":347,"y":647},"time":0.066155},{"point":{"x":351,"y":648},"time":0.083078},{"point":{"x":354,"y":648.5},"time":0.099203},{"point":{"x":356.5,"y":649.5},"time":0.114686},{"point":{"x":359,"y":650.5},"time":0.132988},{"point":{"x":361,"y":651.5},"time":0.149692},{"point":{"x":366,"y":653},"time":0.166488},{"point":{"x":375,"y":653},"time":0.182951},{"point":{"x":385.5,"y":651},"time":0.199637},{"point":{"x":396,"y":649},"time":0.216325},{"point":{"x":404.5,"y":648.5},"time":0.233162},{"point":{"x":410,"y":648},"time":0.249373},{"point":{"x":416.5,"y":648},"time":0.26406},{"point":{"x":424,"y":647},"time":0.282983},{"point":{"x":430.5,"y":644.5},"time":0.299699},{"point":{"x":437.5,"y":640.5},"time":0.317925},{"point":{"x":444,"y":635.5},"time":0.332916},{"point":{"x":449.5,"y":630},"time":0.349685},{"point":{"x":455,"y":623.5},"time":0.366807},{"point":{"x":461,"y":616.5},"time":0.383631},{"point":{"x":465,"y":610.5},"time":0.399566},{"point":{"x":468.5,"y":603.5},"time":0.414064},{"point":{"x":472,"y":596},"time":0.433249},{"point":{"x":474,"y":590.5},"time":0.449593},{"point":{"x":476.5,"y":584},"time":0.466191},{"point":{"x":479,"y":577},"time":0.482866},{"point":{"x":481.5,"y":569},"time":0.499604},{"point":{"x":485,"y":560},"time":0.516359},{"point":{"x":489,"y":549.5},"time":0.533466},{"point":{"x":493,"y":541},"time":0.54945},{"point":{"x":500.5,"y":529},"time":0.56406},{"point":{"x":511.5,"y":513.5},"time":0.583041},{"point":{"x":522,"y":501.5},"time":0.599909},{"point":{"x":533.5,"y":490},"time":0.616305},{"point":{"x":547,"y":479.5},"time":0.633961},{"point":{"x":560,"y":471.5},"time":0.649764},{"point":{"x":574.5,"y":464.5},"time":0.666226},{"point":{"x":590,"y":458.5},"time":0.683564},{"point":{"x":602,"y":455},"time":0.69957},{"point":{"x":616.5,"y":452},"time":0.714442},{"point":{"x":634.5,"y":451.5},"time":0.7331},{"point":{"x":648.5,"y":452},"time":0.749714},{"point":{"x":661.5,"y":454},"time":0.766596},{"point":{"x":673,"y":457.5},"time":0.783311},{"point":{"x":681,"y":463},"time":0.799694},{"point":{"x":687,"y":469.5},"time":0.817365},{"point":{"x":691,"y":478},"time":0.833068},{"point":{"x":693.5,"y":485},"time":0.848833},{"point":{"x":695,"y":495.5},"time":0.86404},{"point":{"x":695,"y":510.5},"time":0.883287},{"point":{"x":692.5,"y":523.5},"time":0.899876},{"point":{"x":688.5,"y":537},"time":0.916301},{"point":{"x":683.5,"y":550.5},"time":0.933436},{"point":{"x":679,"y":562.5},"time":0.9497},{"point":{"x":673.5,"y":575.5},"time":0.96645},{"point":{"x":666.5,"y":588.5},"time":0.983147},{"point":{"x":657.5,"y":602.5},"time":0.99968},{"point":{"x":649.5,"y":613.5},"time":1.0134},{"point":{"x":635.5,"y":630},"time":1.03301},{"point":{"x":623,"y":642},"time":1.04963},{"point":{"x":608.5,"y":654},"time":1.06634},{"point":{"x":593,"y":665},"time":1.08341},{"point":{"x":578.5,"y":673.5},"time":1.09989},{"point":{"x":564.5,"y":680.5},"time":1.11634},{"point":{"x":551.5,"y":684.5},"time":1.13359},{"point":{"x":543,"y":686},"time":1.14908},{"point":{"x":532.5,"y":686.5},"time":1.16397},{"point":{"x":521,"y":685.5},"time":1.18327},{"point":{"x":513.5,"y":682.5},"time":1.20031},{"point":{"x":506.5,"y":678},"time":1.21672},{"point":{"x":500.5,"y":672},"time":1.23331},{"point":{"x":496.5,"y":665.5},"time":1.24995},{"point":{"x":494,"y":659},"time":1.2665},{"point":{"x":493,"y":651},"time":1.28376},{"point":{"x":493,"y":644.5},"time":1.29961},{"point":{"x":493.5,"y":636},"time":1.31409},{"point":{"x":496,"y":626},"time":1.33351},{"point":{"x":498.5,"y":618.5},"time":1.34972},{"point":{"x":502.5,"y":611},"time":1.36647},{"point":{"x":508.5,"y":603},"time":1.38317},{"point":{"x":516,"y":595},"time":1.39994},{"point":{"x":525,"y":587},"time":1.41654},{"point":{"x":534,"y":579},"time":1.43347},{"point":{"x":539.5,"y":574.5},"time":1.44889},{"point":{"x":546,"y":570.5},"time":1.46418},{"point":{"x":555,"y":566},"time":1.48312},{"point":{"x":564.5,"y":562.5},"time":1.50017},{"point":{"x":574.5,"y":559},"time":1.51642},{"point":{"x":585,"y":556.5},"time":1.53323},{"point":{"x":593.5,"y":555},"time":1.54996},{"point":{"x":601.5,"y":555},"time":1.56649},{"point":{"x":609.5,"y":555.5},"time":1.58336},{"point":{"x":616,"y":557},"time":1.59914},{"point":{"x":624.5,"y":560},"time":1.61412},{"point":{"x":636,"y":566.5},"time":1.63316},{"point":{"x":645,"y":573.5},"time":1.64997},{"point":{"x":654,"y":581},"time":1.66653},{"point":{"x":664.5,"y":588.5},"time":1.68312},{"point":{"x":676,"y":596},"time":1.69974},{"point":{"x":689,"y":603.5},"time":1.71648},{"point":{"x":702,"y":611},"time":1.73323},{"point":{"x":711.5,"y":617.5},"time":1.74887},{"point":{"x":723.5,"y":625.5},"time":1.76428},{"point":{"x":739,"y":635},"time":1.78347},{"point":{"x":752,"y":642},"time":1.79974},{"point":{"x":765,"y":649},"time":1.81677},{"point":{"x":779.5,"y":655.5},"time":1.83308},{"point":{"x":795,"y":661},"time":1.84979},{"point":{"x":811.5,"y":665},"time":1.86656},{"point":{"x":827.5,"y":668},"time":1.88421},{"point":{"x":842,"y":671},"time":1.90072},{"point":{"x":852.5,"y":672.5},"time":1.91347},{"point":{"x":870.5,"y":673},"time":1.93181},{"point":{"x":885.5,"y":672},"time":1.94849},{"point":{"x":900.5,"y":669.5},"time":1.96708},{"point":{"x":915.5,"y":666.5},"time":1.98317},{"point":{"x":930,"y":661.5},"time":1.99991},{"point":{"x":944.5,"y":655},"time":2.01656},{"point":{"x":959,"y":648},"time":2.03339},{"point":{"x":970,"y":642},"time":2.0493},{"point":{"x":986.5,"y":632.5},"time":2.06655},{"point":{"x":996,"y":626},"time":2.07977},{"point":{"x":1010,"y":614},"time":2.09986},{"point":{"x":1019,"y":603},"time":2.11642},{"point":{"x":1027,"y":592},"time":2.13348},{"point":{"x":1034,"y":581.5},"time":2.15001},{"point":{"x":1039,"y":571.5},"time":2.1668},{"point":{"x":1043,"y":561.5},"time":2.1837},{"point":{"x":1045.5,"y":553},"time":2.19972},{"point":{"x":1048,"y":540.5},"time":2.21423},{"point":{"x":1050,"y":524},"time":2.23325},{"point":{"x":1050,"y":512},"time":2.24984},{"point":{"x":1048,"y":501.5},"time":2.26671},{"point":{"x":1045,"y":492},"time":2.28307},{"point":{"x":1041,"y":482.5},"time":2.29978},{"point":{"x":1036.5,"y":474.5},"time":2.31643},{"point":{"x":1030,"y":467.5},"time":2.33328},{"point":{"x":1024.5,"y":462.5},"time":2.3492},{"point":{"x":1015.5,"y":457},"time":2.36401},{"point":{"x":1005,"y":452.5},"time":2.38311},{"point":{"x":996,"y":450.5},"time":2.39971},{"point":{"x":987,"y":449.5},"time":2.4165},{"point":{"x":976,"y":449.5},"time":2.43308},{"point":{"x":964,"y":451},"time":2.44976},{"point":{"x":951,"y":454},"time":2.46655},{"point":{"x":937.5,"y":458},"time":2.48338},{"point":{"x":928,"y":462},"time":2.49915},{"point":{"x":914.5,"y":467.5},"time":2.51399},{"point":{"x":897,"y":477},"time":2.53321},{"point":{"x":881.5,"y":487},"time":2.54986},{"point":{"x":866,"y":499},"time":2.56647},{"point":{"x":850,"y":512.5},"time":2.58315},{"point":{"x":837,"y":526},"time":2.59988},{"point":{"x":826.5,"y":540},"time":2.61686},{"point":{"x":818.5,"y":553.5},"time":2.63385},{"point":{"x":813,"y":563.5},"time":2.64951},{"point":{"x":806.5,"y":578.5},"time":2.66449},{"point":{"x":796.5,"y":597.5},"time":2.68365},{"point":{"x":785,"y":615},"time":2.70027},{"point":{"x":774,"y":631.5},"time":2.71693},{"point":{"x":763,"y":647.5},"time":2.73359},{"point":{"x":752.5,"y":665},"time":2.75025},{"point":{"x":742.5,"y":682.5},"time":2.76663},{"point":{"x":732,"y":700},"time":2.78376},{"point":{"x":724,"y":712.5},"time":2.79988},{"point":{"x":712.5,"y":728.5},"time":2.81405},{"point":{"x":698,"y":748},"time":2.83325},{"point":{"x":685,"y":765},"time":2.84992},{"point":{"x":671.5,"y":781.5},"time":2.86706}],"lengths":[{"length":0,"time":0.682619},{"length":2.5,"time":0.683821},{"length":9.46419,"time":0.713297},{"length":10.9642,"time":0.731355},{"length":14.3183,"time":0.746529},{"length":18.4414,"time":0.763453},{"length":21.4828,"time":0.779581},{"length":24.1754,"time":0.795063},{"length":26.868,"time":0.813364},{"length":29.104,"time":0.83007},{"length":34.3242,"time":0.846919},{"length":43.3242,"time":0.863329},{"length":54.013,"time":0.880015},{"length":64.7017,"time":0.896705},{"length":73.2164,"time":0.913542},{"length":78.7391,"time":0.929753},{"length":85.2391,"time":0.944441},{"length":92.8055,"time":0.963365},{"length":99.7697,"time":0.980081},{"length":107.832,"time":0.998308},{"length":116.033,"time":1.0133},{"length":123.811,"time":1.03007},{"length":132.325,"time":1.04719},{"length":141.545,"time":1.06402},{"length":148.756,"time":1.07995},{"length":156.582,"time":1.09445},{"length":164.859,"time":1.11364},{"length":170.711,"time":1.12998},{"length":177.675,"time":1.14658},{"length":185.108,"time":1.16325},{"length":193.49,"time":1.17999},{"length":203.146,"time":1.19675},{"length":214.383,"time":1.21386},{"length":223.777,"time":1.22987},{"length":237.928,"time":1.24446},{"length":256.934,"time":1.26346},{"length":272.879,"time":1.28044},{"length":289.143,"time":1.2967},{"length":306.246,"time":1.31435},{"length":321.51,"time":1.33016},{"length":337.611,"time":1.34662},{"length":354.232,"time":1.364},{"length":366.732,"time":1.37999},{"length":381.539,"time":1.39486},{"length":399.546,"time":1.41352},{"length":413.555,"time":1.43011},{"length":426.708,"time":1.447},{"length":438.729,"time":1.46375},{"length":448.437,"time":1.48011},{"length":457.283,"time":1.49781},{"length":466.677,"time":1.51356},{"length":474.11,"time":1.52924},{"length":484.717,"time":1.54454},{"length":499.717,"time":1.56372},{"length":512.955,"time":1.58028},{"length":527.035,"time":1.5967},{"length":541.431,"time":1.61392},{"length":554.247,"time":1.6301},{"length":568.363,"time":1.64685},{"length":583.128,"time":1.66355},{"length":599.771,"time":1.68009},{"length":613.372,"time":1.6938},{"length":635.011,"time":1.71342},{"length":652.339,"time":1.73004},{"length":671.161,"time":1.74677},{"length":690.167,"time":1.76382},{"length":706.975,"time":1.7803},{"length":722.627,"time":1.79675},{"length":736.229,"time":1.81401},{"length":744.86,"time":1.82949},{"length":755.372,"time":1.84438},{"length":766.916,"time":1.86369},{"length":774.993,"time":1.88072},{"length":783.315,"time":1.89714},{"length":791.8,"time":1.91381},{"length":799.432,"time":1.93037},{"length":806.397,"time":1.94692},{"length":814.459,"time":1.96418},{"length":820.959,"time":1.98003},{"length":829.474,"time":1.99451},{"length":839.781,"time":2.01393},{"length":847.687,"time":2.03014},{"length":856.187,"time":2.04691},{"length":866.187,"time":2.06359},{"length":877.153,"time":2.08036},{"length":889.194,"time":2.09701},{"length":901.236,"time":2.11389},{"length":908.342,"time":2.12931},{"length":915.974,"time":2.14463},{"length":926.037,"time":2.1636},{"length":936.161,"time":2.18067},{"length":946.756,"time":2.19707},{"length":957.549,"time":2.21368},{"length":966.181,"time":2.23039},{"length":974.181,"time":2.24703},{"length":982.196,"time":2.26378},{"length":988.867,"time":2.27957},{"length":997.881,"time":2.29454},{"length":1011.09,"time":2.31359},{"length":1022.49,"time":2.3304},{"length":1034.21,"time":2.34696},{"length":1047.11,"time":2.36355},{"length":1060.84,"time":2.38017},{"length":1075.85,"time":2.39691},{"length":1090.86,"time":2.41366},{"length":1102.37,"time":2.4293},{"length":1116.79,"time":2.44471},{"length":1134.97,"time":2.46391},{"length":1149.73,"time":2.48018},{"length":1164.5,"time":2.49721},{"length":1180.39,"time":2.51352},{"length":1196.84,"time":2.53022},{"length":1213.81,"time":2.54699},{"length":1230.09,"time":2.56465},{"length":1244.9,"time":2.58116},{"length":1255.51,"time":2.59425},{"length":1273.51,"time":2.61225},{"length":1288.55,"time":2.62893},{"length":1303.75,"time":2.64752},{"length":1319.05,"time":2.66361},{"length":1334.39,"time":2.68037},{"length":1350.28,"time":2.6971},{"length":1366.38,"time":2.71401},{"length":1378.91,"time":2.72974},{"length":1397.95,"time":2.74711},{"length":1409.46,"time":2.76022},{"length":1427.9,"time":2.7803},{"length":1442.11,"time":2.79686},{"length":1455.71,"time":2.81392},{"length":1468.33,"time":2.83046},{"length":1479.51,"time":2.84725},{"length":1490.28,"time":2.86419},{"length":1499.14,"time":2.88019},{"length":1511.89,"time":2.8948},{"length":1528.51,"time":2.91388},{"length":1540.51,"time":2.93032},{"length":1551.2,"time":2.94716},{"length":1561.16,"time":2.96352},{"length":1571.47,"time":2.98029},{"length":1580.65,"time":2.99689},{"length":1590.2,"time":3.01376},{"length":1597.64,"time":3.02966},{"length":1608.18,"time":3.04447},{"length":1619.61,"time":3.06357},{"length":1628.83,"time":3.08017},{"length":1637.88,"time":3.09695},{"length":1648.88,"time":3.11354},{"length":1660.98,"time":3.13026},{"length":1674.32,"time":3.14701},{"length":1688.4,"time":3.16383},{"length":1698.7,"time":3.1796},{"length":1713.28,"time":3.19444},{"length":1733.19,"time":3.21368},{"length":1751.64,"time":3.23037},{"length":1771.24,"time":3.24695},{"length":1792.18,"time":3.26362},{"length":1810.92,"time":3.28034},{"length":1828.42,"time":3.29731},{"length":1844.11,"time":3.31431},{"length":1855.52,"time":3.32997},{"length":1871.87,"time":3.34495},{"length":1893.34,"time":3.36411},{"length":1914.28,"time":3.38073},{"length":1934.11,"time":3.39739},{"length":1953.53,"time":3.41405},{"length":1973.94,"time":3.43084},{"length":1994.09,"time":3.44713},{"length":2014.5,"time":3.46433},{"length":2029.34,"time":3.48037},{"length":2049.05,"time":3.49461},{"length":2073.35,"time":3.51375},{"length":2094.75,"time":3.53039},{"length":2116.07,"time":3.54753}]}],"intersections":[]}]}
