{"id":"84A33024-EA1E-4B9F-A305-811E07CCCFB9","name":"default_84A33024-EA1E-4B9F-A305-811E07CCCFB9","drawings":[{"id":"AE0FABC2-A424-4D9A-AA1C-CC95010C29C1","strokes":[{"id":"22FFEE49-60F8-4CAE-A8FE-193282DF6934","time":"2.47733","segments":[{"data":{"point":{"x":336,"y":650},"time":0.002204}},{"data":{"point":{"x":335.5,"y":650},"time":0.00642598}},{"data":{"point":{"x":340.5,"y":650.5},"time":0.041414}},{"data":{"point":{"x":346.5,"y":652},"time":0.063375}},{"data":{"point":{"x":352.5,"y":653},"time":0.081282}},{"data":{"point":{"x":356.5,"y":653.5},"time":0.093456}},{"data":{"point":{"x":361,"y":653.5},"time":0.105641}},{"data":{"point":{"x":367.5,"y":653.5},"time":0.120389}},{"data":{"point":{"x":375,"y":653.5},"time":0.13695}},{"data":{"point":{"x":383.5,"y":653},"time":0.153947}},{"data":{"point":{"x":392.5,"y":652.5},"time":0.170594}},{"data":{"point":{"x":402.5,"y":651},"time":0.187545}},{"data":{"point":{"x":413,"y":649.5},"time":0.203949}},{"data":{"point":{"x":423,"y":647.5},"time":0.221006}},{"data":{"point":{"x":431,"y":645.5},"time":0.237102}},{"data":{"point":{"x":441.5,"y":642.5},"time":0.25154}},{"data":{"point":{"x":454.5,"y":639},"time":0.271453}},{"data":{"point":{"x":465.5,"y":634.5},"time":0.287789}},{"data":{"point":{"x":477.5,"y":629},"time":0.305324}},{"data":{"point":{"x":489.5,"y":623},"time":0.321431}},{"data":{"point":{"x":501.5,"y":616},"time":0.337555}},{"data":{"point":{"x":514,"y":607.5},"time":0.35416}},{"data":{"point":{"x":526.5,"y":599.5},"time":0.370712}},{"data":{"point":{"x":537,"y":592},"time":0.386477}},{"data":{"point":{"x":551.5,"y":582.5},"time":0.401302}},{"data":{"point":{"x":573,"y":569},"time":0.420614}},{"data":{"point":{"x":591,"y":558.5},"time":0.437302}},{"data":{"point":{"x":609.5,"y":548.5},"time":0.453867}},{"data":{"point":{"x":626.5,"y":541},"time":0.470922}},{"data":{"point":{"x":645,"y":535},"time":0.487353}},{"data":{"point":{"x":666,"y":529.5},"time":0.503955}},{"data":{"point":{"x":689,"y":524.5},"time":0.520732}},{"data":{"point":{"x":712.5,"y":522},"time":0.537986}},{"data":{"point":{"x":730.5,"y":521.5},"time":0.551461}},{"data":{"point":{"x":756,"y":522},"time":0.570611}},{"data":{"point":{"x":773,"y":525},"time":0.587371}},{"data":{"point":{"x":788.5,"y":529},"time":0.604966}},{"data":{"point":{"x":801,"y":534},"time":0.620976}},{"data":{"point":{"x":812,"y":540},"time":0.637591}},{"data":{"point":{"x":820,"y":548.5},"time":0.654923}},{"data":{"point":{"x":824,"y":558},"time":0.670869}},{"data":{"point":{"x":826,"y":566},"time":0.686726}},{"data":{"point":{"x":824.5,"y":580.5},"time":0.703938}},{"data":{"point":{"x":821.5,"y":589.5},"time":0.717249}},{"data":{"point":{"x":811.5,"y":604.5},"time":0.737849}},{"data":{"point":{"x":799,"y":618.5},"time":0.754375}},{"data":{"point":{"x":784.5,"y":633},"time":0.771544}},{"data":{"point":{"x":769.5,"y":649},"time":0.787432}},{"data":{"point":{"x":758,"y":664.5},"time":0.803582}},{"data":{"point":{"x":753,"y":677},"time":0.820737}},{"data":{"point":{"x":754,"y":686},"time":0.835691}},{"data":{"point":{"x":765.5,"y":696},"time":0.850941}},{"data":{"point":{"x":790.5,"y":702.5},"time":0.870433}}],"length":[{"data":{"data":0,"time":0.00224096}},{"data":{"data":0.5,"time":0.00646698}},{"data":{"data":5.52494,"time":0.04147}},{"data":{"data":11.7096,"time":0.06343}},{"data":{"data":17.7924,"time":0.081333}},{"data":{"data":21.8235,"time":0.093491}},{"data":{"data":26.3235,"time":0.105811}},{"data":{"data":32.8235,"time":0.120413}},{"data":{"data":40.3235,"time":0.136973}},{"data":{"data":48.8382,"time":0.153974}},{"data":{"data":57.8521,"time":0.170661}},{"data":{"data":67.9639,"time":0.187576}},{"data":{"data":78.5705,"time":0.203984}},{"data":{"data":88.7686,"time":0.221041}},{"data":{"data":97.0148,"time":0.237135}},{"data":{"data":107.935,"time":0.251577}},{"data":{"data":121.398,"time":0.271491}},{"data":{"data":133.283,"time":0.287844}},{"data":{"data":146.483,"time":0.30538}},{"data":{"data":159.9,"time":0.321577}},{"data":{"data":173.792,"time":0.337596}},{"data":{"data":188.908,"time":0.354303}},{"data":{"data":203.749,"time":0.370755}},{"data":{"data":216.652,"time":0.386521}},{"data":{"data":233.987,"time":0.40135}},{"data":{"data":259.374,"time":0.420714}},{"data":{"data":280.213,"time":0.437352}},{"data":{"data":301.243,"time":0.453917}},{"data":{"data":319.824,"time":0.470984}},{"data":{"data":339.272,"time":0.487407}},{"data":{"data":360.981,"time":0.504008}},{"data":{"data":384.518,"time":0.520785}},{"data":{"data":408.15,"time":0.538067}},{"data":{"data":426.157,"time":0.551545}},{"data":{"data":451.662,"time":0.570667}},{"data":{"data":468.925,"time":0.587432}},{"data":{"data":484.933,"time":0.605026}},{"data":{"data":498.396,"time":0.621037}},{"data":{"data":510.926,"time":0.637654}},{"data":{"data":522.598,"time":0.655019}},{"data":{"data":532.906,"time":0.670934}},{"data":{"data":541.152,"time":0.686793}},{"data":{"data":555.73,"time":0.704006}},{"data":{"data":565.216,"time":0.717322}},{"data":{"data":583.244,"time":0.737999}},{"data":{"data":602.013,"time":0.754446}},{"data":{"data":622.519,"time":0.771599}},{"data":{"data":644.45,"time":0.787477}},{"data":{"data":663.751,"time":0.803619}},{"data":{"data":677.214,"time":0.820775}},{"data":{"data":686.269,"time":0.835753}},{"data":{"data":701.509,"time":0.850991}},{"data":{"data":727.34,"time":0.87048}}]},{"id":"DB3533AA-7272-4892-8639-796011E73C6F","time":"4.29538","segments":[{"data":{"point":{"x":290,"y":850},"time":0.00253898}},{"data":{"point":{"x":275,"y":834},"time":0.025279}},{"data":{"point":{"x":269,"y":830.5},"time":0.042233}},{"data":{"point":{"x":265,"y":824.5},"time":0.062086}},{"data":{"point":{"x":261,"y":813.5},"time":0.084658}},{"data":{"point":{"x":252,"y":784.5},"time":0.122236}},{"data":{"point":{"x":246,"y":760},"time":0.139807}},{"data":{"point":{"x":243,"y":744.5},"time":0.152677}},{"data":{"point":{"x":239,"y":720},"time":0.169302}},{"data":{"point":{"x":236.5,"y":693.5},"time":0.186005}},{"data":{"point":{"x":236,"y":665},"time":0.202645}},{"data":{"point":{"x":237,"y":641.5},"time":0.218179}},{"data":{"point":{"x":241.5,"y":608},"time":0.233252}},{"data":{"point":{"x":250.5,"y":565.5},"time":0.252554}},{"data":{"point":{"x":259,"y":532},"time":0.269453}},{"data":{"point":{"x":271.5,"y":498.5},"time":0.285874}},{"data":{"point":{"x":290.5,"y":465.5},"time":0.302564}},{"data":{"point":{"x":319.5,"y":431.5},"time":0.319305}},{"data":{"point":{"x":358.5,"y":397},"time":0.336034}},{"data":{"point":{"x":401,"y":366.5},"time":0.352809}},{"data":{"point":{"x":437,"y":344.5},"time":0.368462}},{"data":{"point":{"x":491,"y":319},"time":0.386108}},{"data":{"point":{"x":534,"y":303},"time":0.40266}},{"data":{"point":{"x":581.5,"y":291},"time":0.419263}},{"data":{"point":{"x":633.5,"y":282},"time":0.43613}},{"data":{"point":{"x":684,"y":278.5},"time":0.452609}},{"data":{"point":{"x":731,"y":279.5},"time":0.469257}},{"data":{"point":{"x":772,"y":286},"time":0.486873}},{"data":{"point":{"x":804,"y":297.5},"time":0.502716}},{"data":{"point":{"x":823,"y":308.5},"time":0.517669}},{"data":{"point":{"x":838,"y":324},"time":0.532659}},{"data":{"point":{"x":842,"y":347.5},"time":0.552261}},{"data":{"point":{"x":832.5,"y":370},"time":0.568882}},{"data":{"point":{"x":810.5,"y":395},"time":0.585578}},{"data":{"point":{"x":777.5,"y":423},"time":0.60209}},{"data":{"point":{"x":735,"y":454},"time":0.619429}},{"data":{"point":{"x":683,"y":489.5},"time":0.635349}},{"data":{"point":{"x":625.5,"y":526.5},"time":0.652542}},{"data":{"point":{"x":577.5,"y":557.5},"time":0.667494}},{"data":{"point":{"x":510.5,"y":605.5},"time":0.682655}},{"data":{"point":{"x":430.5,"y":673.5},"time":0.702137}},{"data":{"point":{"x":378,"y":732},"time":0.718844}},{"data":{"point":{"x":345,"y":782},"time":0.735865}},{"data":{"point":{"x":333.5,"y":822},"time":0.752659}},{"data":{"point":{"x":348,"y":842},"time":0.768895}},{"data":{"point":{"x":392,"y":842.5},"time":0.785415}},{"data":{"point":{"x":462,"y":823},"time":0.802322}},{"data":{"point":{"x":527.5,"y":802},"time":0.81756}},{"data":{"point":{"x":572,"y":789},"time":0.827857}}],"length":[{"data":{"data":0,"time":0.00257599}},{"data":{"data":21.9317,"time":0.025326}},{"data":{"data":28.8779,"time":0.042285}},{"data":{"data":36.089,"time":0.062137}},{"data":{"data":47.7937,"time":0.084761}},{"data":{"data":78.1582,"time":0.122296}},{"data":{"data":103.382,"time":0.139853}},{"data":{"data":119.17,"time":0.152702}},{"data":{"data":143.994,"time":0.169362}},{"data":{"data":170.612,"time":0.186033}},{"data":{"data":199.116,"time":0.202674}},{"data":{"data":222.638,"time":0.21821}},{"data":{"data":256.438,"time":0.233285}},{"data":{"data":299.881,"time":0.252589}},{"data":{"data":334.442,"time":0.269488}},{"data":{"data":370.199,"time":0.28596}},{"data":{"data":408.277,"time":0.302601}},{"data":{"data":452.965,"time":0.319344}},{"data":{"data":505.035,"time":0.336075}},{"data":{"data":557.346,"time":0.352849}},{"data":{"data":599.536,"time":0.368503}},{"data":{"data":659.255,"time":0.38615}},{"data":{"data":705.135,"time":0.402706}},{"data":{"data":754.127,"time":0.419312}},{"data":{"data":806.9,"time":0.436176}},{"data":{"data":857.521,"time":0.452656}},{"data":{"data":904.532,"time":0.469308}},{"data":{"data":946.044,"time":0.486991}},{"data":{"data":980.048,"time":0.502767}},{"data":{"data":1002,"time":0.517726}},{"data":{"data":1023.57,"time":0.532692}},{"data":{"data":1047.41,"time":0.552295}},{"data":{"data":1071.83,"time":0.568918}},{"data":{"data":1105.13,"time":0.585613}},{"data":{"data":1148.41,"time":0.602126}},{"data":{"data":1201.02,"time":0.619553}},{"data":{"data":1263.98,"time":0.63538}},{"data":{"data":1332.36,"time":0.652572}},{"data":{"data":1389.5,"time":0.667526}},{"data":{"data":1471.92,"time":0.682687}},{"data":{"data":1576.91,"time":0.702169}},{"data":{"data":1655.51,"time":0.718904}},{"data":{"data":1715.42,"time":0.735907}},{"data":{"data":1757.04,"time":0.752694}},{"data":{"data":1781.75,"time":0.76893}},{"data":{"data":1825.75,"time":0.785451}},{"data":{"data":1898.41,"time":0.802359}},{"data":{"data":1967.2,"time":0.817597}},{"data":{"data":2013.56,"time":0.827901}}]},{"id":"9112455B-BF55-4D20-ACAE-C4A9C757157C","time":"5.61981","segments":[{"data":{"point":{"x":618.5,"y":912.5},"time":0.00130504}},{"data":{"point":{"x":617,"y":908.5},"time":0.013059}},{"data":{"point":{"x":617.5,"y":902},"time":0.032717}},{"data":{"point":{"x":639.5,"y":884},"time":0.066114}},{"data":{"point":{"x":691,"y":852.5},"time":0.097618}},{"data":{"point":{"x":755.5,"y":815.5},"time":0.115773}},{"data":{"point":{"x":788.5,"y":798.5},"time":0.128624}},{"data":{"point":{"x":831,"y":779},"time":0.144932}},{"data":{"point":{"x":871,"y":764.5},"time":0.161747}},{"data":{"point":{"x":898.5,"y":760},"time":0.178311}},{"data":{"point":{"x":907,"y":765},"time":0.195071}},{"data":{"point":{"x":893,"y":784.5},"time":0.211662}},{"data":{"point":{"x":853,"y":816.5},"time":0.228278}},{"data":{"point":{"x":817.5,"y":841.5},"time":0.244031}},{"data":{"point":{"x":764.5,"y":874.5},"time":0.262066}},{"data":{"point":{"x":741,"y":887.5},"time":0.276901}},{"data":{"point":{"x":724,"y":898},"time":0.294838}},{"data":{"point":{"x":730,"y":898},"time":0.311711}},{"data":{"point":{"x":759,"y":886},"time":0.32851}},{"data":{"point":{"x":800,"y":868.5},"time":0.344869}},{"data":{"point":{"x":844.5,"y":850.5},"time":0.363}},{"data":{"point":{"x":882,"y":837},"time":0.379611}},{"data":{"point":{"x":899,"y":830.5},"time":0.394554}},{"data":{"point":{"x":911,"y":825.5},"time":0.408711}},{"data":{"point":{"x":914,"y":824},"time":0.428425}},{"data":{"point":{"x":911.5,"y":825},"time":0.445004}},{"data":{"point":{"x":910.5,"y":826.5},"time":0.461723}},{"data":{"point":{"x":915,"y":823.5},"time":0.478468}},{"data":{"point":{"x":930,"y":811.5},"time":0.495313}},{"data":{"point":{"x":953,"y":791.5},"time":0.512991}},{"data":{"point":{"x":976,"y":768.5},"time":0.529226}},{"data":{"point":{"x":993.5,"y":746.5},"time":0.543569}},{"data":{"point":{"x":1014.5,"y":715.5},"time":0.558368}},{"data":{"point":{"x":1031.5,"y":677},"time":0.578281}},{"data":{"point":{"x":1035,"y":646.5},"time":0.594738}},{"data":{"point":{"x":1023.5,"y":620},"time":0.611605}},{"data":{"point":{"x":999,"y":601},"time":0.628066}},{"data":{"point":{"x":971.5,"y":588.5},"time":0.64498}},{"data":{"point":{"x":947,"y":580.5},"time":0.66198}},{"data":{"point":{"x":925.5,"y":578},"time":0.678382}},{"data":{"point":{"x":903,"y":585.5},"time":0.693763}},{"data":{"point":{"x":853.5,"y":621.5},"time":0.711726}},{"data":{"point":{"x":813,"y":661.5},"time":0.728454}},{"data":{"point":{"x":783,"y":696.5},"time":0.744845}},{"data":{"point":{"x":767,"y":724},"time":0.761578}},{"data":{"point":{"x":762.5,"y":745.5},"time":0.778186}},{"data":{"point":{"x":767,"y":763.5},"time":0.794639}},{"data":{"point":{"x":781.5,"y":777},"time":0.811688}},{"data":{"point":{"x":814,"y":778},"time":0.828268}},{"data":{"point":{"x":849,"y":768.5},"time":0.843924}},{"data":{"point":{"x":914,"y":744.5},"time":0.861617}},{"data":{"point":{"x":958.5,"y":723.5},"time":0.875052}},{"data":{"point":{"x":1025.5,"y":683.5},"time":0.895109}},{"data":{"point":{"x":1059,"y":653},"time":0.911664}},{"data":{"point":{"x":1063,"y":630},"time":0.928426}},{"data":{"point":{"x":1049.5,"y":625},"time":0.940155}}],"length":[{"data":{"data":0,"time":0.00133902}},{"data":{"data":4.272,"time":0.013258}},{"data":{"data":10.7912,"time":0.03282}},{"data":{"data":39.2165,"time":0.066168}},{"data":{"data":99.5862,"time":0.0976771}},{"data":{"data":173.945,"time":0.115808}},{"data":{"data":211.067,"time":0.12865}},{"data":{"data":257.827,"time":0.144957}},{"data":{"data":300.374,"time":0.161777}},{"data":{"data":328.239,"time":0.178343}},{"data":{"data":338.101,"time":0.195102}},{"data":{"data":362.106,"time":0.211695}},{"data":{"data":413.331,"time":0.228315}},{"data":{"data":456.751,"time":0.244081}},{"data":{"data":519.185,"time":0.262116}},{"data":{"data":546.041,"time":0.276953}},{"data":{"data":566.022,"time":0.294877}},{"data":{"data":572.022,"time":0.31175}},{"data":{"data":603.407,"time":0.328549}},{"data":{"data":647.985,"time":0.344909}},{"data":{"data":695.988,"time":0.36306}},{"data":{"data":735.844,"time":0.379674}},{"data":{"data":754.044,"time":0.394601}},{"data":{"data":767.044,"time":0.408755}},{"data":{"data":770.398,"time":0.42847}},{"data":{"data":773.091,"time":0.445052}},{"data":{"data":774.894,"time":0.461774}},{"data":{"data":780.302,"time":0.478518}},{"data":{"data":799.511,"time":0.495389}},{"data":{"data":829.991,"time":0.513071}},{"data":{"data":862.518,"time":0.529303}},{"data":{"data":890.629,"time":0.543625}},{"data":{"data":928.072,"time":0.558412}},{"data":{"data":970.159,"time":0.578338}},{"data":{"data":1000.86,"time":0.594784}},{"data":{"data":1029.75,"time":0.61165}},{"data":{"data":1060.75,"time":0.628113}},{"data":{"data":1090.96,"time":0.645042}},{"data":{"data":1116.73,"time":0.662066}},{"data":{"data":1138.38,"time":0.678448}},{"data":{"data":1162.09,"time":0.693831}},{"data":{"data":1223.3,"time":0.711796}},{"data":{"data":1280.22,"time":0.728522}},{"data":{"data":1326.32,"time":0.744907}},{"data":{"data":1358.14,"time":0.761641}},{"data":{"data":1380.1,"time":0.77824}},{"data":{"data":1398.66,"time":0.794694}},{"data":{"data":1418.47,"time":0.811797}},{"data":{"data":1450.98,"time":0.828342}},{"data":{"data":1487.25,"time":0.843999}},{"data":{"data":1556.54,"time":0.861694}},{"data":{"data":1605.75,"time":0.87513}},{"data":{"data":1683.78,"time":0.895188}},{"data":{"data":1729.08,"time":0.911743}},{"data":{"data":1752.43,"time":0.928508}},{"data":{"data":1766.82,"time":0.940314}}]},{"id":"9A927D25-1404-4826-9FFB-4AC76E612A4F","time":"7.10448","segments":[{"data":{"point":{"x":154,"y":887},"time":0.00505102}},{"data":{"point":{"x":145.5,"y":880},"time":0.016263}},{"data":{"point":{"x":150.5,"y":863.5},"time":0.047509}},{"data":{"point":{"x":177,"y":837.5},"time":0.083167}},{"data":{"point":{"x":182.5,"y":854.5},"time":0.110907}},{"data":{"point":{"x":170.5,"y":884},"time":0.128085}},{"data":{"point":{"x":162,"y":899.5},"time":0.143015}},{"data":{"point":{"x":151.5,"y":916},"time":0.160725}},{"data":{"point":{"x":149,"y":922},"time":0.177026}},{"data":{"point":{"x":154.5,"y":920.5},"time":0.193671}},{"data":{"point":{"x":168.5,"y":909.5},"time":0.210454}},{"data":{"point":{"x":188,"y":893.5},"time":0.227477}},{"data":{"point":{"x":206.5,"y":882.5},"time":0.24579}},{"data":{"point":{"x":214,"y":885},"time":0.260368}},{"data":{"point":{"x":216.5,"y":907.5},"time":0.276913}},{"data":{"point":{"x":215.5,"y":925.5},"time":0.293634}},{"data":{"point":{"x":217.5,"y":937.5},"time":0.31056}},{"data":{"point":{"x":224.5,"y":946},"time":0.328085}},{"data":{"point":{"x":238,"y":949.5},"time":0.34496}},{"data":{"point":{"x":257.5,"y":945},"time":0.359288}},{"data":{"point":{"x":282.5,"y":931.5},"time":0.375774}},{"data":{"point":{"x":312.5,"y":910},"time":0.392184}},{"data":{"point":{"x":337.5,"y":889},"time":0.409124}},{"data":{"point":{"x":370.5,"y":861.5},"time":0.424381}},{"data":{"point":{"x":405.5,"y":830},"time":0.444073}},{"data":{"point":{"x":426.5,"y":810},"time":0.461074}},{"data":{"point":{"x":443,"y":793.5},"time":0.477664}},{"data":{"point":{"x":460,"y":776},"time":0.49393}},{"data":{"point":{"x":483.5,"y":755},"time":0.510538}},{"data":{"point":{"x":512,"y":732.5},"time":0.527155}},{"data":{"point":{"x":543,"y":713},"time":0.544519}},{"data":{"point":{"x":568.5,"y":701.5},"time":0.560255}},{"data":{"point":{"x":608,"y":689.5},"time":0.574043}},{"data":{"point":{"x":663.5,"y":684},"time":0.5936}},{"data":{"point":{"x":694.5,"y":687},"time":0.610482}}],"length":[{"data":{"data":0,"time":0.00508898}},{"data":{"data":11.0114,"time":0.016307}},{"data":{"data":28.2523,"time":0.047807}},{"data":{"data":65.3771,"time":0.083221}},{"data":{"data":83.2447,"time":0.110939}},{"data":{"data":115.092,"time":0.128119}},{"data":{"data":132.77,"time":0.143052}},{"data":{"data":152.327,"time":0.160753}},{"data":{"data":158.827,"time":0.177114}},{"data":{"data":164.528,"time":0.1937}},{"data":{"data":182.333,"time":0.210486}},{"data":{"data":207.557,"time":0.227522}},{"data":{"data":229.08,"time":0.245929}},{"data":{"data":236.986,"time":0.260401}},{"data":{"data":259.624,"time":0.276941}},{"data":{"data":277.652,"time":0.293663}},{"data":{"data":289.817,"time":0.310601}},{"data":{"data":300.829,"time":0.328176}},{"data":{"data":314.775,"time":0.345001}},{"data":{"data":334.787,"time":0.359329}},{"data":{"data":363.2,"time":0.375817}},{"data":{"data":400.108,"time":0.392229}},{"data":{"data":432.758,"time":0.409168}},{"data":{"data":475.714,"time":0.424427}},{"data":{"data":522.802,"time":0.444118}},{"data":{"data":551.802,"time":0.461123}},{"data":{"data":575.136,"time":0.477714}},{"data":{"data":599.534,"time":0.493981}},{"data":{"data":631.05,"time":0.510588}},{"data":{"data":667.361,"time":0.527209}},{"data":{"data":703.984,"time":0.544579}},{"data":{"data":731.958,"time":0.560353}},{"data":{"data":773.24,"time":0.574087}},{"data":{"data":829.012,"time":0.593642}},{"data":{"data":860.157,"time":0.610608}}]},{"id":"A17888A7-F1BA-48FB-933A-9E573A795A2A","time":"8.94888","segments":[{"data":{"point":{"x":925.5,"y":929},"time":0.000544965}},{"data":{"point":{"x":925.5,"y":927},"time":0.00502199}},{"data":{"point":{"x":929.5,"y":916.5},"time":0.034149}},{"data":{"point":{"x":934.5,"y":910.5},"time":0.046625}},{"data":{"point":{"x":947,"y":901},"time":0.066233}},{"data":{"point":{"x":974,"y":887.5},"time":0.083709}},{"data":{"point":{"x":1001,"y":877.5},"time":0.098402}},{"data":{"point":{"x":1053,"y":862},"time":0.116985}},{"data":{"point":{"x":1085,"y":858.5},"time":0.133451}},{"data":{"point":{"x":1097.5,"y":863},"time":0.149375}},{"data":{"point":{"x":1088.5,"y":879},"time":0.165889}},{"data":{"point":{"x":1060,"y":900},"time":0.182903}},{"data":{"point":{"x":1029.5,"y":920.5},"time":0.200375}},{"data":{"point":{"x":1011,"y":933},"time":0.214398}},{"data":{"point":{"x":996,"y":944},"time":0.232718}},{"data":{"point":{"x":998.5,"y":945.5},"time":0.249497}},{"data":{"point":{"x":1016.5,"y":941.5},"time":0.266344}},{"data":{"point":{"x":1042.5,"y":931.5},"time":0.282846}},{"data":{"point":{"x":1070,"y":922},"time":0.299649}},{"data":{"point":{"x":1101,"y":910},"time":0.316062}},{"data":{"point":{"x":1131,"y":898},"time":0.332709}},{"data":{"point":{"x":1159,"y":885.5},"time":0.349607}},{"data":{"point":{"x":1176,"y":876.5},"time":0.364418}},{"data":{"point":{"x":1198,"y":858},"time":0.382746}},{"data":{"point":{"x":1212.5,"y":838.5},"time":0.399497}},{"data":{"point":{"x":1223.5,"y":814},"time":0.416124}},{"data":{"point":{"x":1229,"y":788},"time":0.432959}},{"data":{"point":{"x":1228.5,"y":760.5},"time":0.449696}},{"data":{"point":{"x":1223.5,"y":732},"time":0.466433}},{"data":{"point":{"x":1218,"y":704},"time":0.484756}},{"data":{"point":{"x":1214.5,"y":682},"time":0.500243}},{"data":{"point":{"x":1209.5,"y":652},"time":0.515187}},{"data":{"point":{"x":1201,"y":615},"time":0.531607}},{"data":{"point":{"x":1191,"y":584},"time":0.547843}},{"data":{"point":{"x":1177.5,"y":552.5},"time":0.566329}},{"data":{"point":{"x":1162,"y":523},"time":0.583134}},{"data":{"point":{"x":1144,"y":494},"time":0.599703}},{"data":{"point":{"x":1122.5,"y":465.5},"time":0.616111}},{"data":{"point":{"x":1096.5,"y":440},"time":0.63266}},{"data":{"point":{"x":1066.5,"y":416.5},"time":0.649582}},{"data":{"point":{"x":1043,"y":400.5},"time":0.664791}},{"data":{"point":{"x":1000.5,"y":376.5},"time":0.683068}},{"data":{"point":{"x":966,"y":360},"time":0.699608}},{"data":{"point":{"x":932,"y":344.5},"time":0.716738}},{"data":{"point":{"x":900.5,"y":331},"time":0.733103}},{"data":{"point":{"x":870.5,"y":318},"time":0.749673}},{"data":{"point":{"x":845,"y":306},"time":0.766222}},{"data":{"point":{"x":825,"y":296},"time":0.78379}},{"data":{"point":{"x":810,"y":286.5},"time":0.800431}},{"data":{"point":{"x":799.5,"y":280.5},"time":0.814762}},{"data":{"point":{"x":782.5,"y":275.5},"time":0.83298}},{"data":{"point":{"x":769.5,"y":275.5},"time":0.849639}},{"data":{"point":{"x":757.5,"y":279.5},"time":0.866405}},{"data":{"point":{"x":746,"y":289.5},"time":0.883118}},{"data":{"point":{"x":732.5,"y":304.5},"time":0.89972}},{"data":{"point":{"x":713.5,"y":325.5},"time":0.916335}},{"data":{"point":{"x":688,"y":352.5},"time":0.934072}},{"data":{"point":{"x":657.5,"y":384},"time":0.95031}},{"data":{"point":{"x":633.5,"y":410},"time":0.964687}},{"data":{"point":{"x":601,"y":452},"time":0.983108}},{"data":{"point":{"x":584,"y":479.5},"time":0.996354}},{"data":{"point":{"x":564,"y":523.5},"time":1.01623}},{"data":{"point":{"x":555.5,"y":554.5},"time":1.03303}},{"data":{"point":{"x":553,"y":584},"time":1.0497}},{"data":{"point":{"x":556,"y":614},"time":1.06628}},{"data":{"point":{"x":567.5,"y":640},"time":1.08295}},{"data":{"point":{"x":588,"y":663},"time":1.09985}},{"data":{"point":{"x":610.5,"y":677},"time":1.11483}},{"data":{"point":{"x":660,"y":685.5},"time":1.13318}},{"data":{"point":{"x":704.5,"y":685.5},"time":1.1497}},{"data":{"point":{"x":739,"y":683},"time":1.16425}},{"data":{"point":{"x":793,"y":675},"time":1.18274}},{"data":{"point":{"x":827,"y":667},"time":1.19949}}],"length":[{"data":{"data":0,"time":0.000557959}},{"data":{"data":2,"time":0.00503999}},{"data":{"data":13.2361,"time":0.034171}},{"data":{"data":21.0464,"time":0.046647}},{"data":{"data":36.7467,"time":0.066268}},{"data":{"data":66.9336,"time":0.083745}},{"data":{"data":95.7259,"time":0.098439}},{"data":{"data":149.987,"time":0.117023}},{"data":{"data":182.178,"time":0.133479}},{"data":{"data":195.463,"time":0.149399}},{"data":{"data":213.821,"time":0.165913}},{"data":{"data":249.222,"time":0.182933}},{"data":{"data":285.971,"time":0.200406}},{"data":{"data":308.298,"time":0.214426}},{"data":{"data":326.899,"time":0.232752}},{"data":{"data":329.815,"time":0.249536}},{"data":{"data":348.254,"time":0.266381}},{"data":{"data":376.111,"time":0.282885}},{"data":{"data":405.205,"time":0.299691}},{"data":{"data":438.447,"time":0.316094}},{"data":{"data":470.758,"time":0.332743}},{"data":{"data":501.421,"time":0.349686}},{"data":{"data":520.657,"time":0.364453}},{"data":{"data":549.401,"time":0.382781}},{"data":{"data":573.701,"time":0.399546}},{"data":{"data":600.557,"time":0.416163}},{"data":{"data":627.133,"time":0.433008}},{"data":{"data":654.637,"time":0.449752}},{"data":{"data":683.573,"time":0.466484}},{"data":{"data":712.108,"time":0.484824}},{"data":{"data":734.384,"time":0.500297}},{"data":{"data":764.798,"time":0.515232}},{"data":{"data":802.762,"time":0.531652}},{"data":{"data":835.335,"time":0.547887}},{"data":{"data":869.606,"time":0.566389}},{"data":{"data":902.93,"time":0.583193}},{"data":{"data":937.062,"time":0.599765}},{"data":{"data":972.762,"time":0.61616}},{"data":{"data":1009.18,"time":0.632709}},{"data":{"data":1047.29,"time":0.649631}},{"data":{"data":1075.72,"time":0.664859}},{"data":{"data":1124.53,"time":0.683135}},{"data":{"data":1162.77,"time":0.699677}},{"data":{"data":1200.14,"time":0.716807}},{"data":{"data":1234.41,"time":0.733173}},{"data":{"data":1267.1,"time":0.749746}},{"data":{"data":1295.28,"time":0.766294}},{"data":{"data":1317.65,"time":0.783945}},{"data":{"data":1335.4,"time":0.80054}},{"data":{"data":1347.49,"time":0.814854}},{"data":{"data":1365.21,"time":0.833056}},{"data":{"data":1378.21,"time":0.849718}},{"data":{"data":1390.86,"time":0.866484}},{"data":{"data":1406.1,"time":0.883249}},{"data":{"data":1426.28,"time":0.899802}},{"data":{"data":1454.6,"time":0.916419}},{"data":{"data":1491.74,"time":0.934194}},{"data":{"data":1535.59,"time":0.950394}},{"data":{"data":1570.97,"time":0.964802}},{"data":{"data":1624.08,"time":0.983197}},{"data":{"data":1656.41,"time":0.996445}},{"data":{"data":1704.74,"time":1.01632}},{"data":{"data":1736.88,"time":1.03312}},{"data":{"data":1766.49,"time":1.04979}},{"data":{"data":1796.64,"time":1.06637}},{"data":{"data":1825.07,"time":1.08306}},{"data":{"data":1855.88,"time":1.09994}},{"data":{"data":1882.38,"time":1.11494}},{"data":{"data":1932.6,"time":1.13327}},{"data":{"data":1977.1,"time":1.1498}},{"data":{"data":2011.69,"time":1.16435}},{"data":{"data":2066.28,"time":1.18282}},{"data":{"data":2101.21,"time":1.19957}}]},{"id":"0AC9FF62-B3B4-4146-A234-BFF1E1849DE9","time":"10.6685","segments":[{"data":{"point":{"x":60,"y":701},"time":0.00129998}},{"data":{"point":{"x":53.5,"y":697},"time":0.018487}},{"data":{"point":{"x":53,"y":694},"time":0.038009}},{"data":{"point":{"x":60.5,"y":684},"time":0.059467}},{"data":{"point":{"x":81.5,"y":660},"time":0.081422}},{"data":{"point":{"x":127.5,"y":620.5},"time":0.118546}},{"data":{"point":{"x":161,"y":600.5},"time":0.14143}},{"data":{"point":{"x":169.5,"y":600},"time":0.154048}},{"data":{"point":{"x":171,"y":608.5},"time":0.164963}},{"data":{"point":{"x":162.5,"y":633},"time":0.180445}},{"data":{"point":{"x":150.5,"y":660},"time":0.197476}},{"data":{"point":{"x":141.5,"y":681},"time":0.213454}},{"data":{"point":{"x":139,"y":692.5},"time":0.230215}},{"data":{"point":{"x":146,"y":693.5},"time":0.246749}},{"data":{"point":{"x":162.5,"y":682},"time":0.264249}},{"data":{"point":{"x":185,"y":663},"time":0.280406}},{"data":{"point":{"x":200.5,"y":650},"time":0.295006}},{"data":{"point":{"x":221.5,"y":633.5},"time":0.313852}},{"data":{"point":{"x":230.5,"y":630.5},"time":0.330566}},{"data":{"point":{"x":233.5,"y":636},"time":0.346982}},{"data":{"point":{"x":233.5,"y":646},"time":0.363829}},{"data":{"point":{"x":234.5,"y":655.5},"time":0.380499}},{"data":{"point":{"x":238.5,"y":662.5},"time":0.397021}},{"data":{"point":{"x":246.5,"y":664},"time":0.415013}},{"data":{"point":{"x":259,"y":659},"time":0.430457}},{"data":{"point":{"x":271.5,"y":649},"time":0.445147}},{"data":{"point":{"x":293,"y":627.5},"time":0.463839}},{"data":{"point":{"x":309,"y":607},"time":0.480326}},{"data":{"point":{"x":320,"y":587},"time":0.496974}},{"data":{"point":{"x":324.5,"y":570.5},"time":0.513716}},{"data":{"point":{"x":323.5,"y":555},"time":0.53044}},{"data":{"point":{"x":317.5,"y":539},"time":0.547205}},{"data":{"point":{"x":307,"y":523.5},"time":0.56357}},{"data":{"point":{"x":297,"y":511.5},"time":0.580996}},{"data":{"point":{"x":282.5,"y":494},"time":0.59505}},{"data":{"point":{"x":263,"y":471},"time":0.613592}},{"data":{"point":{"x":251.5,"y":456},"time":0.627254}},{"data":{"point":{"x":237,"y":432},"time":0.646713}},{"data":{"point":{"x":232,"y":411},"time":0.663497}},{"data":{"point":{"x":231.5,"y":387.5},"time":0.680068}},{"data":{"point":{"x":238,"y":362.5},"time":0.697062}},{"data":{"point":{"x":250.5,"y":337.5},"time":0.713271}},{"data":{"point":{"x":266,"y":315},"time":0.730179}},{"data":{"point":{"x":280,"y":299.5},"time":0.744745}},{"data":{"point":{"x":309.5,"y":277},"time":0.764683}},{"data":{"point":{"x":332,"y":265},"time":0.777576}},{"data":{"point":{"x":372.5,"y":249.5},"time":0.795335}},{"data":{"point":{"x":413,"y":238},"time":0.812159}},{"data":{"point":{"x":463,"y":225.5},"time":0.828453}},{"data":{"point":{"x":524,"y":214},"time":0.846981}},{"data":{"point":{"x":589.5,"y":207.5},"time":0.86421}},{"data":{"point":{"x":625,"y":205.5},"time":0.875305}}],"length":[{"data":{"data":0,"time":0.00133699}},{"data":{"data":7.63217,"time":0.018536}},{"data":{"data":10.6735,"time":0.038062}},{"data":{"data":23.1735,"time":0.059527}},{"data":{"data":55.064,"time":0.081457}},{"data":{"data":115.696,"time":0.118608}},{"data":{"data":154.712,"time":0.141466}},{"data":{"data":163.227,"time":0.154072}},{"data":{"data":171.858,"time":0.164986}},{"data":{"data":197.791,"time":0.180467}},{"data":{"data":227.337,"time":0.1975}},{"data":{"data":250.185,"time":0.213477}},{"data":{"data":261.953,"time":0.230241}},{"data":{"data":269.024,"time":0.246774}},{"data":{"data":289.136,"time":0.264284}},{"data":{"data":318.586,"time":0.280442}},{"data":{"data":338.815,"time":0.295044}},{"data":{"data":365.522,"time":0.313892}},{"data":{"data":375.009,"time":0.330605}},{"data":{"data":381.274,"time":0.347023}},{"data":{"data":391.274,"time":0.363871}},{"data":{"data":400.827,"time":0.380544}},{"data":{"data":408.889,"time":0.397066}},{"data":{"data":417.028,"time":0.415186}},{"data":{"data":430.491,"time":0.430523}},{"data":{"data":446.499,"time":0.445196}},{"data":{"data":476.905,"time":0.463887}},{"data":{"data":502.909,"time":0.480397}},{"data":{"data":525.735,"time":0.497046}},{"data":{"data":542.837,"time":0.513771}},{"data":{"data":558.37,"time":0.530499}},{"data":{"data":575.458,"time":0.547257}},{"data":{"data":594.179,"time":0.563628}},{"data":{"data":609.8,"time":0.581052}},{"data":{"data":632.526,"time":0.595095}},{"data":{"data":662.68,"time":0.613652}},{"data":{"data":681.581,"time":0.627313}},{"data":{"data":709.621,"time":0.646761}},{"data":{"data":731.208,"time":0.663545}},{"data":{"data":754.714,"time":0.680118}},{"data":{"data":780.545,"time":0.697111}},{"data":{"data":808.496,"time":0.713321}},{"data":{"data":835.818,"time":0.730233}},{"data":{"data":856.704,"time":0.744798}},{"data":{"data":893.806,"time":0.764754}},{"data":{"data":919.306,"time":0.777646}},{"data":{"data":962.67,"time":0.79539}},{"data":{"data":1004.77,"time":0.812216}},{"data":{"data":1056.31,"time":0.828511}},{"data":{"data":1118.38,"time":0.847037}},{"data":{"data":1184.21,"time":0.864344}},{"data":{"data":1219.76,"time":0.875381}}]}],"intersections":[]}]}
